neoscr/__init__.py
neoscr/_modidx.py
neoscr/cli.py
neoscr/core.py
neoscr/utils.py
neoscr-2.1.2.dist-info/LICENSE
neoscr-2.1.2.dist-info/METADATA
neoscr-2.1.2.dist-info/WHEEL
neoscr-2.1.2.dist-info/entry_points.txt
neoscr-2.1.2.dist-info/top_level.txt
neoscr-2.1.2.dist-info/RECORD
