Metadata-Version: 2.1
Name: neoscr
Version: 2.1.2
Summary: Wrapper to query the SCR api
Home-page: https://github.com/datarisk-io/neoscr
Author: João Nogueira
Author-email: joao.nogueira@datarisk.io
License: Apache Software License 2.0
Keywords: nbdev jupyter notebook python
Platform: UNKNOWN
Classifier: Development Status :: 4 - Beta
Classifier: Intended Audience :: Developers
Classifier: Natural Language :: English
Classifier: Programming Language :: Python :: 3.7
Classifier: Programming Language :: Python :: 3.8
Classifier: Programming Language :: Python :: 3.9
Classifier: Programming Language :: Python :: 3.10
Classifier: License :: OSI Approved :: Apache Software License
Requires-Python: >=3.7
License-File: LICENSE
Requires-Dist: fastcore
Requires-Dist: pandas
Requires-Dist: requests
Provides-Extra: dev
Requires-Dist: nbdev ; extra == 'dev'
Requires-Dist: jupyter ; extra == 'dev'
